Workbook

Sheet Sheet1
A1: domain | B1: query_file | C1: match_file | D1: query | E1: direct_match | F1: query_section | G1: match_section | H1: direct_sim | I1: hidden_sim | J1: direct_degree | K1: hidden_degree
A2: Fiscal Support | B2: 上海市财政支持做好碳达峰碳中和工作的实施意见.docx | C2: 上海市财政支持做好碳达峰碳中和工作的实施意见.docx | D2: 上海市财政支持做好碳达峰碳中和工作的实施意见 | E2: 为深入贯彻落实党中央、国务院关于碳达峰碳中和重大战略决策，根据《财政部关于印发〈财政支持做好碳达峰碳中和工作的意见〉的通知》《中共上海市委 上海市人民政府关于完整准确全面贯彻新发展理念做好碳达峰碳中和工作的实施意见》《上海市人民政府关于印发〈上海市碳达峰实施方案〉的通知》等文件精神，按照市委、市政府关于碳达峰碳中和工作的统一部署要求，充分发挥财政职能作用，以实现减污降碳协同增效为总抓手，促进本市经济社会发展全面绿色低碳转型，现就本市财政支持做好碳达峰碳中和工作提出如下实施意见 | F2: 空 | G2: 空 | H2: 0.91921383 | I2: 0.91921383 | J2: 12.5 | K2: 12.5
A3: Fiscal Support | B3: 上海市财政支持做好碳达峰碳中和工作的实施意见.docx | C3: 上海市财政支持做好碳达峰碳中和工作的实施意见.docx | D3: 为深入贯彻落实党中央、国务院关于碳达峰碳中和重大战略决策，根据《财政部关于印发〈财政支持做好碳达峰碳中和工作的意见〉的通知》《中共上海市委 上海市人民政府关于完整准确全面贯彻新发展理念做好碳达峰碳中和工作的实施意见》《上海市人民政府关于印发〈上海市碳达峰实施方案〉的通知》等文件精神，按照市委、市政府关于碳达峰碳中和工作的统一部署要求，充分发挥财政职能作用，以实现减污降碳协同增效为总抓手，促进本市经济社会发展全面绿色低碳转型，现就本市财政支持做好碳达峰碳中和工作提出如下实施意见 | E3: 为深入贯彻落实党中央、国务院关于碳达峰碳中和重大战略决策，根据《财政部关于印发〈财政支持做好碳达峰碳中和工作的意见〉的通知》《中共上海市委 上海市人民政府关于完整准确全面贯彻新发展理念做好碳达峰碳中和工作的实施意见》《上海市人民政府关于印发〈上海市碳达峰实施方案〉的通知》等文件精神，按照市委、市政府关于碳达峰碳中和工作的统一部署要求，充分发挥财政职能作用，以实现减污降碳协同增效为总抓手，促进本市经济社会发展全面绿色低碳转型，现就本市财政支持做好碳达峰碳中和工作提出如下实施意见 | F3: 空 | G3: 空 | H3: 0.98096311 | I3: 0.98096311 | J3: 0 | K3: 0
A4: Fiscal Support | B4: 上海市财政支持做好碳达峰碳中和工作的实施意见.docx | C4: 上海市财政支持做好碳达峰碳中和工作的实施意见.docx | D4: （一）指导思想 | E4: （一）指导思想 | F4: 一 | G4: 一 | H4: 0.79864627 | I4: 0.79864627 | J4: 0 | K4: 0
A5: Fiscal Support | B5: 上海市财政支持做好碳达峰碳中和工作的实施意见.docx | C5: 上海市财政支持做好碳达峰碳中和工作的实施意见.docx | D5: 以习近平新时代中国特色社会主义思想为指导，全面贯彻落实党的二十大精神，深入贯彻习近平生态文明思想，紧紧围绕深化上海五个中心和生态之城建设，立足新发展阶段，完整、准确、全面贯彻新发展理念，服务构建新发展格局，厚植高质量发展的绿色底色 | E5: 以习近平新时代中国特色社会主义思想为指导，全面贯彻落实党的二十大精神，深入贯彻习近平生态文明思想，紧紧围绕深化上海五个中心和生态之城建设，立足新发展阶段，完整、准确、全面贯彻新发展理念，服务构建新发展格局，厚植高质量发展的绿色底色 | F5: 一 | G5: 一 | H5: 0.926278 | I5: 0.926278 | J5: 0 | K5: 0
A6: Fiscal Support | B6: 上海市财政支持做好碳达峰碳中和工作的实施意见.docx | C6: 上海市财政支持做好碳达峰碳中和工作的实施意见.docx | D6: 坚持先立后破，不断强化内生动力、实践自主行动，加快构建有利于促进资源高效利用和绿色低碳发展的财政政策支持体系，推动有为政府和有效市场更好结合，支持上海在全国率先走出一条生态优先、绿色低碳的高质量发展道路，确保如期实现碳达峰碳中和 | E6: 坚持先立后破，不断强化内生动力、实践自主行动，加快构建有利于促进资源高效利用和绿色低碳发展的财政政策支持体系，推动有为政府和有效市场更好结合，支持上海在全国率先走出一条生态优先、绿色低碳的高质量发展道路，确保如期实现碳达峰碳中和 | F6: 一 | G6: 一 | H6: 0.94528884 | I6: 0.94528884 | J6: 0 | K6: 0
A7: Fiscal Support | B7: 上海市财政支持做好碳达峰碳中和工作的实施意见.docx | C7: 上海市财政支持做好碳达峰碳中和工作的实施意见.docx | D7: （二）基本原则 | E7: （二）基本原则 | F7: 一 | G7: 一 | H7: 0.7718513 | I7: 0.7718513 | J7: 0 | K7: 0
A8: Fiscal Support | B8: 上海市财政支持做好碳达峰碳中和工作的实施意见.docx | C8: 上海市财政支持做好碳达峰碳中和工作的实施意见.docx | D8: 1.系统谋划，因地制宜 | E8: 1.系统谋划，因地制宜 | F8: 一 | G8: 一 | H8: 0.89764971 | I8: 0.89764971 | J8: 0 | K8: 0
A9: Fiscal Support | B9: 上海市财政支持做好碳达峰碳中和工作的实施意见.docx | C9: 上海市财政支持做好碳达峰碳中和工作的实施意见.docx | D9: 坚持系统观念，加强财政支持政策与国家和本市十四五规划纲要衔接，立足本市环境资源禀赋和经济社会发展实际，正确处理高质量发展和高水平保护的关系，构建具有上海特点的财政支持碳达峰碳中和政策体系，支持加快探索出一条与超大城市相适应的绿色低碳高质量发展道路 | E9: 坚持系统观念，加强财政支持政策与国家和本市十四五规划纲要衔接，立足本市环境资源禀赋和经济社会发展实际，正确处理高质量发展和高水平保护的关系，构建具有上海特点的财政支持碳达峰碳中和政策体系，支持加快探索出一条与超大城市相适应的绿色低碳高质量发展道路 | F9: 一 | G9: 一 | H9: 0.94761777 | I9: 0.94761777 | J9: 0 | K9: 0
A10: Fiscal Support | B10: 上海市财政支持做好碳达峰碳中和工作的实施意见.docx | C10: 上海市财政支持做好碳达峰碳中和工作的实施意见.docx | D10: 2.重点攻坚，协同治理 | E10: 2.重点攻坚，协同治理 | F10: 一 | G10: 一 | H10: 0.90653896 | I10: 0.90653896 | J10: 0 | K10: 0
A11: Fiscal Support | B11: 上海市财政支持做好碳达峰碳中和工作的实施意见.docx | C11: 上海市财政支持做好碳达峰碳中和工作的实施意见.docx | D11: 实现重点突破，落实积极的财政政策要提升效能，更加注重精准、可持续的要求，从重点方向和领域入手，注重点面结合、标本兼治、分类施策 | E11: 实现重点突破，落实积极的财政政策要提升效能，更加注重精准、可持续的要求，从重点方向和领域入手，注重点面结合、标本兼治、分类施策 | F11: 一 | G11: 一 | H11: 0.92760235 | I11: 0.92760235 | J11: 0 | K11: 0
A12: Fiscal Support | B12: 上海市财政支持做好碳达峰碳中和工作的实施意见.docx | C12: 上海市财政支持做好碳达峰碳中和工作的实施意见.docx | D12: 加强财政资源统筹，推动资金、税收、政府采购等政策协同发力，强化目标协同、部门协同、区域协同、政策协同，积极稳妥推进碳达峰碳中和 | E12: 加强财政资源统筹，推动资金、税收、政府采购等政策协同发力，强化目标协同、部门协同、区域协同、政策协同，积极稳妥推进碳达峰碳中和 | F12: 一 | G12: 一 | H12: 0.91329789 | I12: 0.91329789 | J12: 0 | K12: 0
A13: Fiscal Support | B13: 上海市财政支持做好碳达峰碳中和工作的实施意见.docx | C13: 上海市财政支持做好碳达峰碳中和工作的实施意见.docx | D13: 3.政府引导，多元投入 | E13: 3.政府引导，多元投入 | F13: 一 | G13: 一 | H13: 0.86010575 | I13: 0.86010575 | J13: 0 | K13: 0
... A30547: Fiscal Support | B30547: 陕西财政支持做好碳达峰碳中和工作的实施意见.docx | C30547: 陕西财政支持做好碳达峰碳中和工作的实施意见.docx | D30547: 加大财政支持做好碳达峰碳中和宣传和科普工作力度，鼓励有条件的地区采取多种方式加强生态文明宣传教育，建设碳达峰碳中和主题科普基地，推动生态文明理念更加深入人心，促进形成绿色低碳发展的良好氛围 | E30547: 加大财政支持做好碳达峰碳中和宣传和科普工作力度，鼓励有条件的地区采取多种方式加强生态文明宣传教育，建设碳达峰碳中和主题科普基地，推动生态文明理念更加深入人心，促进形成绿色低碳发展的良好氛围 | F30547: 四 | G30547: 四 | H30547: 0.90507483 | I30547: 0.90507483 | J30547: 0 | K30547: 0

Sheet Sheet2
A1: sim | B1: response | C1: source
A2: 0.05 | B2: =AVERAGEIFS(Sheet1!J:J,Sheet1!H:H,">"&A2,Sheet1!H:H,"<"&A3,Sheet1!B:B,"财政支持做好碳达峰碳中和工作的意见.docx") -> #DIV/0! | C2: =-AVERAGEIFS(Sheet1!J:J,Sheet1!H:H,">"&A2,Sheet1!H:H,"<"&A3,Sheet1!C:C,"财政支持做好碳达峰碳中和工作的意见.docx") -> #DIV/0!
A3: 0.1 | B3: =AVERAGEIFS(Sheet1!J:J,Sheet1!H:H,">"&A3,Sheet1!H:H,"<"&A4,Sheet1!B:B,"财政支持做好碳达峰碳中和工作的意见.docx") -> #DIV/0! | C3: =-AVERAGEIFS(Sheet1!J:J,Sheet1!H:H,">"&A3,Sheet1!H:H,"<"&A4,Sheet1!C:C,"财政支持做好碳达峰碳中和工作的意见.docx") -> #DIV/0!
A4: 0.15 | B4: =AVERAGEIFS(Sheet1!J:J,Sheet1!H:H,">"&A4,Sheet1!H:H,"<"&A5,Sheet1!B:B,"财政支持做好碳达峰碳中和工作的意见.docx") -> #DIV/0! | C4: =-AVERAGEIFS(Sheet1!J:J,Sheet1!H:H,">"&A4,Sheet1!H:H,"<"&A5,Sheet1!C:C,"财政支持做好碳达峰碳中和工作的意见.docx") -> #DIV/0!
A5: 0.2 | B5: =AVERAGEIFS(Sheet1!J:J,Sheet1!H:H,">"&A5,Sheet1!H:H,"<"&A6,Sheet1!B:B,"财政支持做好碳达峰碳中和工作的意见.docx") -> #DIV/0! | C5: =-AVERAGEIFS(Sheet1!J:J,Sheet1!H:H,">"&A5,Sheet1!H:H,"<"&A6,Sheet1!C:C,"财政支持做好碳达峰碳中和工作的意见.docx") -> #DIV/0!
A6: 0.25 | B6: =AVERAGEIFS(Sheet1!J:J,Sheet1!H:H,">"&A6,Sheet1!H:H,"<"&A7,Sheet1!B:B,"财政支持做好碳达峰碳中和工作的意见.docx") -> 2.6666667 | C6: =-AVERAGEIFS(Sheet1!J:J,Sheet1!H:H,">"&A6,Sheet1!H:H,"<"&A7,Sheet1!C:C,"财政支持做好碳达峰碳中和工作的意见.docx") -> #DIV/0!
A7: 0.3 | B7: =AVERAGEIFS(Sheet1!J:J,Sheet1!H:H,">"&A7,Sheet1!H:H,"<"&A8,Sheet1!B:B,"财政支持做好碳达峰碳中和工作的意见.docx") -> 1.2083333 | C7: =-AVERAGEIFS(Sheet1!J:J,Sheet1!H:H,">"&A7,Sheet1!H:H,"<"&A8,Sheet1!C:C,"财政支持做好碳达峰碳中和工作的意见.docx") -> #DIV/0!
A8: 0.35 | B8: =AVERAGEIFS(Sheet1!J:J,Sheet1!H:H,">"&A8,Sheet1!H:H,"<"&A9,Sheet1!B:B,"财政支持做好碳达峰碳中和工作的意见.docx") -> 0.38095238 | C8: =-AVERAGEIFS(Sheet1!J:J,Sheet1!H:H,">"&A8,Sheet1!H:H,"<"&A9,Sheet1!C:C,"财政支持做好碳达峰碳中和工作的意见.docx") -> -0.25
A9: 0.4 | B9: =AVERAGEIFS(Sheet1!J:J,Sheet1!H:H,">"&A9,Sheet1!H:H,"<"&A10,Sheet1!B:B,"财政支持做好碳达峰碳中和工作的意见.docx") -> 1.296875 | C9: =-AVERAGEIFS(Sheet1!J:J,Sheet1!H:H,">"&A9,Sheet1!H:H,"<"&A10,Sheet1!C:C,"财政支持做好碳达峰碳中和工作的意见.docx") -> -0.16176471
A10: 0.45 | B10: =AVERAGEIFS(Sheet1!J:J,Sheet1!H:H,">"&A10,Sheet1!H:H,"<"&A11,Sheet1!B:B,"财政支持做好碳达峰碳中和工作的意见.docx") -> 1.28125 | C10: =-AVERAGEIFS(Sheet1!J:J,Sheet1!H:H,">"&A10,Sheet1!H:H,"<"&A11,Sheet1!C:C,"财政支持做好碳达峰碳中和工作的意见.docx") -> -0.31097561
A11: 0.5 | B11: =AVERAGEIFS(Sheet1!J:J,Sheet1!H:H,">"&A11,Sheet1!H:H,"<"&A12,Sheet1!B:B,"财政支持做好碳达峰碳中和工作的意见.docx") -> 0.44444444 | C11: =-AVERAGEIFS(Sheet1!J:J,Sheet1!H:H,">"&A11,Sheet1!H:H,"<"&A12,Sheet1!C:C,"财政支持做好碳达峰碳中和工作的意见.docx") -> 0.018115942
A12: 0.55 | B12: =AVERAGEIFS(Sheet1!J:J,Sheet1!H:H,">"&A12,Sheet1!H:H,"<"&A13,Sheet1!B:B,"财政支持做好碳达峰碳中和工作的意见.docx") -> 1.3040541 | C12: =-AVERAGEIFS(Sheet1!J:J,Sheet1!H:H,">"&A12,Sheet1!H:H,"<"&A13,Sheet1!C:C,"财政支持做好碳达峰碳中和工作的意见.docx") -> -0.012195122
A13: 0.6 | B13: =AVERAGEIFS(Sheet1!J:J,Sheet1!H:H,">"&A13,Sheet1!H:H,"<"&A14,Sheet1!B:B,"财政支持做好碳达峰碳中和工作的意见.docx") -> 0.56388889 | C13: =-AVERAGEIFS(Sheet1!J:J,Sheet1!H:H,">"&A13,Sheet1!H:H,"<"&A14,Sheet1!C:C,"财政支持做好碳达峰碳中和工作的意见.docx") -> -0.25668449
... A21: 1 | B21: =AVERAGEIFS(Sheet1!J:J,Sheet1!H:H,">"&A21,Sheet1!H:H,"<"&A22,Sheet1!B:B,"财政支持做好碳达峰碳中和工作的意见.docx") -> #DIV/0! | C21: =-AVERAGEIFS(Sheet1!J:J,Sheet1!H:H,">"&A21,Sheet1!H:H,"<"&A22,Sheet1!C:C,"财政支持做好碳达峰碳中和工作的意见.docx") -> #DIV/0!
